wise_api/__init__.py
wise_api/client.py
wise_api/crypto.py
wise_api/exceptions.py
wise_api/py.typed
wise_api/utils.py
wise_api-0.2.0.dist-info/METADATA
wise_api-0.2.0.dist-info/WHEEL
wise_api-0.2.0.dist-info/RECORD
