Metadata-Version: 2.1
Name: wise-api
Version: 0.2.0
Summary: Python API client for the Wise API
Home-page: https://github.com/financica/python-wise-api
License: MIT
Keywords: wise,transferwise,api
Author: Jerome Leclanche
Author-email: jerome@leclan.ch
Requires-Python: >=3.10,<4.0
Classifier: Development Status :: 3 - Alpha
Classifier: Environment :: Web Environment
Classifier: Intended Audience :: Developers
Classifier: License :: OSI Approved :: MIT License
Classifier: Operating System :: OS Independent
Classifier: Programming Language :: Python :: 3
Classifier: Programming Language :: Python :: 3.10
Classifier: Programming Language :: Python :: 3.11
Classifier: Topic :: Internet :: WWW/HTTP
Classifier: Typing :: Typed
Requires-Dist: pycryptodome (>=3.16.0,<4.0.0)
Requires-Dist: requests (>=2.28.1,<3.0.0)
Project-URL: Repository, https://github.com/financica/python-wise-api
